zwo/__init__.py
zwo/camera.py
zwo/capabilities.py
zwo/enums.py
zwo/errors.py
zwo/gps.py
zwo/info.py
zwo/lib.py
zwo/mode.py
zwo/py.typed
zwo/time.py
zwo/utils.py
zwo/version.py
sdk/asi/137/include/ASICamera2.h
sdk/asi/137/include/ASICameraDll2.cs
sdk/asi/137/lib/README.txt
sdk/asi/137/lib/asi.rules
sdk/asi/137/lib/armv6/libASICamera2.a
sdk/asi/137/lib/armv6/libASICamera2.so
sdk/asi/137/lib/armv6/libASICamera2.so.1.37
sdk/asi/137/lib/armv7/libASICamera2.a
sdk/asi/137/lib/armv7/libASICamera2.so
sdk/asi/137/lib/armv7/libASICamera2.so.1.37
sdk/asi/137/lib/armv8/libASICamera2.a
sdk/asi/137/lib/armv8/libASICamera2.so
sdk/asi/137/lib/armv8/libASICamera2.so.1.37
sdk/asi/137/lib/mac/libASICamera2.a
sdk/asi/137/lib/mac/libASICamera2.dylib
sdk/asi/137/lib/mac/libASICamera2.dylib.1.37
sdk/asi/137/lib/x64/libASICamera2.a
sdk/asi/137/lib/x64/libASICamera2.dll
sdk/asi/137/lib/x64/libASICamera2.lib
sdk/asi/137/lib/x64/libASICamera2.so
sdk/asi/137/lib/x64/libASICamera2.so.1.37
sdk/asi/137/lib/x86/libASICamera2.a
sdk/asi/137/lib/x86/libASICamera2.dll
sdk/asi/137/lib/x86/libASICamera2.lib
sdk/asi/137/lib/x86/libASICamera2.so
sdk/asi/137/lib/x86/libASICamera2.so.1.37
zwo-0.5.0.dist-info/METADATA
zwo-0.5.0.dist-info/WHEEL
zwo-0.5.0.dist-info/entry_points.txt
zwo-0.5.0.dist-info/licenses/LICENSE
zwo-0.5.0.dist-info/RECORD
