Metadata-Version: 2.4
Name: zwo
Version: 0.5.0
Summary: Modern python bindings for ZWO ASI astronomical cameras
Project-URL: Source, https://github.com/michealroberts/zwoasi
Project-URL: Issues, https://github.com/michealroberts/zwoasi/issues
Project-URL: PullRequests, https://github.com/michealroberts/zwoasi/pulls
Project-URL: Discussions, https://github.com/michealroberts/zwoasi/discussions
Author-email: Michael Roberts <michael@observerly.com>
Maintainer-email: Michael Roberts <michael@observerly.com>
License: MIT License
License-File: LICENSE
Keywords: astrophotography,zwoasi
Classifier: Development Status :: 3 - Alpha
Classifier: Intended Audience :: Developers
Classifier: License :: OSI Approved :: MIT License
Classifier: Programming Language :: Python :: 3.13
Requires-Python: >=3.13
Requires-Dist: pydantic>=2.10.6
